metabolinks/__init__.py
metabolinks/cdaccessors.py
metabolinks/checks.py
metabolinks/chemont.py
metabolinks/create_local_dbs.py
metabolinks/dataio.py
metabolinks/datasets.py
metabolinks/exp_accessors.py
metabolinks/features.py
metabolinks/fetch_dbs.py
metabolinks/formulae.py
metabolinks/peak_alignment.py
metabolinks/similarity.py
metabolinks/taxonomy.py
metabolinks/transformations.py
metabolinks/utils.py
metabolinks/data/sample_data.xlsx
notebooks/MassTRIX_output.tsv
notebooks/blacklist.txt
notebooks/peak_alignment_xcel.ipynb
notebooks/sample_data.xlsx
notebooks/taxonomy_annotation_example.ipynb
tests/__init__.py
tests/test_dataio.py
tests/test_transformations.py
metabolinks-1.0.0.dist-info/AUTHORS.md
metabolinks-1.0.0.dist-info/LICENSE
metabolinks-1.0.0.dist-info/METADATA
metabolinks-1.0.0.dist-info/WHEEL
metabolinks-1.0.0.dist-info/top_level.txt
metabolinks-1.0.0.dist-info/RECORD
