Metadata-Version: 2.1
Name: metabolinks
Version: 1.0.0
Summary: A set of tools for high-resolution MS metabolomics data analysis
Home-page: https://github.com/aeferreira/metabolinks
Author: António Ferreira
Author-email: aeferreira@fc.ul.pt
Maintainer: António Ferreira
Maintainer-email: aeferreira@fc.ul.pt
License: MIT
Download-URL: https://github.com/aeferreira/metabolinks
Keywords: Metabolomics,Mass Spectrometry,Data Analysis,Ultra-high resolution MS
Platform: UNKNOWN
Classifier: Development Status :: 3 - Alpha
Classifier: Intended Audience :: Science/Research
Classifier: Intended Audience :: Education
Classifier: Natural Language :: English
Classifier: Operating System :: OS Independent
Classifier: Programming Language :: Python
Classifier: License :: OSI Approved :: MIT License
Classifier: Programming Language :: Python
Classifier: Programming Language :: Python :: 3
Classifier: Programming Language :: Python :: 3.6
Classifier: Programming Language :: Python :: 3.7
Classifier: Programming Language :: Python :: 3.8
Classifier: Topic :: Scientific/Engineering :: Bio-Informatics
Classifier: Topic :: Scientific/Engineering :: Chemistry
Classifier: Topic :: Scientific/Engineering :: Information Analysis
Requires-Dist: requests
Requires-Dist: numpy
Requires-Dist: pandas (>=0.25)
Requires-Dist: xlrd
Requires-Dist: xlsxwriter
Requires-Dist: pandas-flavor
Requires-Dist: pytest
Requires-Dist: matplotlib (>=2.0)
